tests/__init__.py
tests/test_yaml_cache.py
yaml_sync/__init__.py
yaml_sync/yaml_sync.py
yaml_sync-0.2.dist-info/METADATA
yaml_sync-0.2.dist-info/WHEEL
yaml_sync-0.2.dist-info/top_level.txt
yaml_sync-0.2.dist-info/RECORD
