Metadata-Version: 2.1
Name: yaml-sync
Version: 0.2
Summary: A simple YAML-based cache for Python
Home-page: https://github.com/organisciak/yaml-cachesync
Author: Peter Organisciak
Author-email: organisciak@gmail.com
Classifier: Development Status :: 3 - Alpha
Classifier: Intended Audience :: Developers
Classifier: License :: OSI Approved :: MIT License
Classifier: Operating System :: OS Independent
Classifier: Programming Language :: Python
Classifier: Programming Language :: Python :: 3
Classifier: Programming Language :: Python :: 3.6
Classifier: Programming Language :: Python :: 3.7
Classifier: Programming Language :: Python :: 3.8
Classifier: Programming Language :: Python :: 3.9
Requires-Dist: PyYAML (>=5.1)
